[
  {
    "id": "8c03a36a-3e00-4920-90c2-60b7f243e397",
    "companyId": null,
    "name": "SEQUENCIA",
    "description": "Funcao",
    "canLeadTeam": false,
    "hierarchyLevel": 0,
    "createdAt": "2026-02-07T09:00:45.282Z",
    "updatedAt": "2026-02-07T09:00:45.282Z"
  },
  {
    "id": "11097455-58e4-43e8-92b0-87f65fdf0b38",
    "companyId": null,
    "name": "1.00",
    "description": "AJUDANTE DE MARTELETEIRO",
    "canLeadTeam": false,
    "hierarchyLevel": 0,
    "createdAt": "2026-02-07T09:00:45.395Z",
    "updatedAt": "2026-02-07T09:00:45.395Z"
  },
  {
    "id": "e818c95d-7e5a-45bd-8d06-d560302a8d60",
    "companyId": null,
    "name": "2.00",
    "description": "AJUDANTE",
    "canLeadTeam": false,
    "hierarchyLevel": 0,
    "createdAt": "2026-02-07T09:00:45.504Z",
    "updatedAt": "2026-02-07T09:00:45.504Z"
  },
  {
    "id": "097c420a-827e-42f2-847d-027eab5e10f2",
    "companyId": null,
    "name": "3.00",
    "description": "ARMADOR",
    "canLeadTeam": false,
    "hierarchyLevel": 0,
    "createdAt": "2026-02-07T09:00:45.617Z",
    "updatedAt": "2026-02-07T09:00:45.617Z"
  },
  {
    "id": "5a328a38-a591-4cfb-8d36-0a3e7e22c905",
    "companyId": null,
    "name": "4.00",
    "description": "AUXILIAR DE TOPOGRAFIA",
    "canLeadTeam": false,
    "hierarchyLevel": 0,
    "createdAt": "2026-02-07T09:00:45.737Z",
    "updatedAt": "2026-02-07T09:00:45.737Z"
  },
  {
    "id": "65423165-01f5-45b0-adb5-334a2b91d6e1",
    "companyId": null,
    "name": "5.00",
    "description": "ENCARREGADO DE ARMA??O",
    "canLeadTeam": false,
    "hierarchyLevel": 0,
    "createdAt": "2026-02-07T09:00:45.876Z",
    "updatedAt": "2026-02-07T09:00:45.876Z"
  },
  {
    "id": "c23a8447-f3d7-4c74-951a-2449bce51e1d",
    "companyId": null,
    "name": "6.00",
    "description": "ENCARREGADO DE MONTAGEM  AT",
    "canLeadTeam": false,
    "hierarchyLevel": 0,
    "createdAt": "2026-02-07T09:00:45.964Z",
    "updatedAt": "2026-02-07T09:00:45.964Z"
  },
  {
    "id": "4b6cea3b-c77d-47a4-bf17-adf35c14b507",
    "companyId": null,
    "name": "7.00",
    "description": "ENCARREGADO DE MONTAGEM",
    "canLeadTeam": false,
    "hierarchyLevel": 0,
    "createdAt": "2026-02-07T09:00:46.059Z",
    "updatedAt": "2026-02-07T09:00:46.059Z"
  },
  {
    "id": "f3126791-4e4f-4fea-be3f-6ce3e9024b19",
    "companyId": null,
    "name": "8.00",
    "description": "CARPINTEIRO",
    "canLeadTeam": false,
    "hierarchyLevel": 0,
    "createdAt": "2026-02-07T09:00:46.156Z",
    "updatedAt": "2026-02-07T09:00:46.156Z"
  },
  {
    "id": "50de6b3e-0e52-489f-b531-73f4f715ef76",
    "companyId": null,
    "name": "9.00",
    "description": "ENCARREGADO DE OBRAS GERAIS",
    "canLeadTeam": false,
    "hierarchyLevel": 0,
    "createdAt": "2026-02-07T09:00:46.254Z",
    "updatedAt": "2026-02-07T09:00:46.254Z"
  },
  {
    "id": "c3ba86e6-d00e-4bbb-9ce7-923d24216293",
    "companyId": null,
    "name": "10.00",
    "description": "MARTELETEIRO",
    "canLeadTeam": false,
    "hierarchyLevel": 0,
    "createdAt": "2026-02-07T09:00:46.352Z",
    "updatedAt": "2026-02-07T09:00:46.352Z"
  },
  {
    "id": "67cd48fc-9351-4f64-b4a8-9f68dd170779",
    "companyId": null,
    "name": "11.00",
    "description": "MEIO OFICIAL ARMADOR",
    "canLeadTeam": false,
    "hierarchyLevel": 0,
    "createdAt": "2026-02-07T09:00:46.454Z",
    "updatedAt": "2026-02-07T09:00:46.454Z"
  },
  {
    "id": "ba8a2623-3c4f-48d5-a665-5392f58cfd0d",
    "companyId": null,
    "name": "12.00",
    "description": "MEIO OFICIAL CARPINTEIRO",
    "canLeadTeam": false,
    "hierarchyLevel": 0,
    "createdAt": "2026-02-07T09:00:46.593Z",
    "updatedAt": "2026-02-07T09:00:46.593Z"
  },
  {
    "id": "93ee5606-5d6b-4e5f-b8d5-b2966bb4f45e",
    "companyId": null,
    "name": "13.00",
    "description": "MEIO OFICIAL ELETRICISTA",
    "canLeadTeam": false,
    "hierarchyLevel": 0,
    "createdAt": "2026-02-07T09:00:46.684Z",
    "updatedAt": "2026-02-07T09:00:46.684Z"
  },
  {
    "id": "fd1aca7b-4a3f-4e53-9d9d-38427c95b97c",
    "companyId": null,
    "name": "14.00",
    "description": "MEIO OFICIAL MONTADOR AT",
    "canLeadTeam": false,
    "hierarchyLevel": 0,
    "createdAt": "2026-02-07T09:00:46.778Z",
    "updatedAt": "2026-02-07T09:00:46.778Z"
  },
  {
    "id": "2147d866-de7f-4cbe-906e-b80f1715e8ff",
    "companyId": null,
    "name": "15.00",
    "description": "MEIO OFICIAL MONTADOR",
    "canLeadTeam": false,
    "hierarchyLevel": 0,
    "createdAt": "2026-02-07T09:00:46.873Z",
    "updatedAt": "2026-02-07T09:00:46.873Z"
  },
  {
    "id": "df320c53-4d73-4f3f-9286-be4896d6cdc4",
    "companyId": null,
    "name": "16.00",
    "description": "MEIO OFICIAL PEDREIRO",
    "canLeadTeam": false,
    "hierarchyLevel": 0,
    "createdAt": "2026-02-07T09:00:46.980Z",
    "updatedAt": "2026-02-07T09:00:46.980Z"
  },
  {
    "id": "50786413-562e-44ab-8d21-1090d1ab4313",
    "companyId": null,
    "name": "17.00",
    "description": "MONTADOR AT",
    "canLeadTeam": false,
    "hierarchyLevel": 0,
    "createdAt": "2026-02-07T09:00:47.073Z",
    "updatedAt": "2026-02-07T09:00:47.073Z"
  },
  {
    "id": "6b9fa198-2616-46a4-98d2-6b31cfb38949",
    "companyId": null,
    "name": "18.00",
    "description": "MONTADOR ESPOREIRO",
    "canLeadTeam": false,
    "hierarchyLevel": 0,
    "createdAt": "2026-02-07T09:00:47.164Z",
    "updatedAt": "2026-02-07T09:00:47.164Z"
  },
  {
    "id": "d0c5a635-0e90-4f7d-a18a-75948c12fae0",
    "companyId": null,
    "name": "19.00",
    "description": "MONTADOR",
    "canLeadTeam": false,
    "hierarchyLevel": 0,
    "createdAt": "2026-02-07T09:00:47.267Z",
    "updatedAt": "2026-02-07T09:00:47.267Z"
  },
  {
    "id": "dfa91f57-c3e3-40b7-ad3c-9e47cc25bead",
    "companyId": null,
    "name": "20.00",
    "description": "MOTORISTA CARRETEIRO",
    "canLeadTeam": false,
    "hierarchyLevel": 0,
    "createdAt": "2026-02-07T09:00:47.346Z",
    "updatedAt": "2026-02-07T09:00:47.346Z"
  },
  {
    "id": "a2342cc6-dd4e-4e4f-bc93-a2a697a9d42a",
    "companyId": null,
    "name": "21.00",
    "description": "MOTORISTA DE CAMINH?O - GUINCHO PESADO COM MUNCK",
    "canLeadTeam": false,
    "hierarchyLevel": 0,
    "createdAt": "2026-02-07T09:00:47.424Z",
    "updatedAt": "2026-02-07T09:00:47.424Z"
  },
  {
    "id": "fce836b2-ecbb-41e3-a827-2135ece56154",
    "companyId": null,
    "name": "22.00",
    "description": "MOTORISTA DE OPERADOR",
    "canLeadTeam": false,
    "hierarchyLevel": 0,
    "createdAt": "2026-02-07T09:00:47.518Z",
    "updatedAt": "2026-02-07T09:00:47.518Z"
  },
  {
    "id": "6d61120c-592d-405f-8c7e-45bcfc96c252",
    "companyId": null,
    "name": "23.00",
    "description": "MOTORISTA DE OPERADOR AT",
    "canLeadTeam": false,
    "hierarchyLevel": 0,
    "createdAt": "2026-02-07T09:00:47.624Z",
    "updatedAt": "2026-02-07T09:00:47.624Z"
  },
  {
    "id": "cdd8594a-83d8-4bd1-94fd-6a21e85913da",
    "companyId": null,
    "name": "24.00",
    "description": "MOTORISTA DE OPERADOR BASCULANTE",
    "canLeadTeam": false,
    "hierarchyLevel": 0,
    "createdAt": "2026-02-07T09:00:47.699Z",
    "updatedAt": "2026-02-07T09:00:47.699Z"
  },
  {
    "id": "6acb9946-10e3-46d9-bc23-d52a5242092c",
    "companyId": null,
    "name": "25.00",
    "description": "MOTORISTA DE OPERADOR DE BETONEIRA",
    "canLeadTeam": false,
    "hierarchyLevel": 0,
    "createdAt": "2026-02-07T09:00:47.796Z",
    "updatedAt": "2026-02-07T09:00:47.796Z"
  },
  {
    "id": "5b4683f5-fb87-4c55-84b7-837abc0e7a70",
    "companyId": null,
    "name": "26.00",
    "description": "MOTORISTA DE OPERADOR DE MUNK",
    "canLeadTeam": false,
    "hierarchyLevel": 0,
    "createdAt": "2026-02-07T09:00:47.907Z",
    "updatedAt": "2026-02-07T09:00:47.907Z"
  },
  {
    "id": "0b32d992-76dc-4780-9161-72381c2104c8",
    "companyId": null,
    "name": "27.00",
    "description": "MOTORISTA DE OPERADOR DE RETRO-ESCAVADEIRA",
    "canLeadTeam": false,
    "hierarchyLevel": 0,
    "createdAt": "2026-02-07T09:00:48.000Z",
    "updatedAt": "2026-02-07T09:00:48.000Z"
  },
  {
    "id": "9537293b-a99e-4099-86f3-e7bf69e67825",
    "companyId": null,
    "name": "28.00",
    "description": "MOTORISTA OPERADOR DE PERFURATRIZ",
    "canLeadTeam": false,
    "hierarchyLevel": 0,
    "createdAt": "2026-02-07T09:00:48.090Z",
    "updatedAt": "2026-02-07T09:00:48.090Z"
  },
  {
    "id": "bbdd4412-795b-4f2d-891d-f489ae9ce464",
    "companyId": null,
    "name": "29.00",
    "description": "NIVELADOR",
    "canLeadTeam": false,
    "hierarchyLevel": 0,
    "createdAt": "2026-02-07T09:00:48.182Z",
    "updatedAt": "2026-02-07T09:00:48.182Z"
  },
  {
    "id": "eb5a7070-1c3d-460c-af83-e4147f63ceaa",
    "companyId": null,
    "name": "30.00",
    "description": "OPERADOR DE M?QUINAS",
    "canLeadTeam": false,
    "hierarchyLevel": 0,
    "createdAt": "2026-02-07T09:00:48.272Z",
    "updatedAt": "2026-02-07T09:00:48.272Z"
  },
  {
    "id": "d6099472-af76-462a-8fe0-8d9129c8b580",
    "companyId": null,
    "name": "31.00",
    "description": "OPERADOR DE MOTOSSERRA",
    "canLeadTeam": false,
    "hierarchyLevel": 0,
    "createdAt": "2026-02-07T09:00:48.382Z",
    "updatedAt": "2026-02-07T09:00:48.382Z"
  },
  {
    "id": "f8c18d6b-e72f-49c1-ad80-176fa9c4277a",
    "companyId": null,
    "name": "32.00",
    "description": "OPERADOR DE RETROESCAVADEIRA",
    "canLeadTeam": false,
    "hierarchyLevel": 0,
    "createdAt": "2026-02-07T09:00:48.487Z",
    "updatedAt": "2026-02-07T09:00:48.487Z"
  },
  {
    "id": "457cef2c-84ad-4485-b42a-65d81d8ee037",
    "companyId": null,
    "name": "33.00",
    "description": "OPERADOR DE TRATOR",
    "canLeadTeam": false,
    "hierarchyLevel": 0,
    "createdAt": "2026-02-07T09:00:48.597Z",
    "updatedAt": "2026-02-07T09:00:48.597Z"
  },
  {
    "id": "6ef9268d-9d59-4f9f-ad7a-337c7d08410b",
    "companyId": null,
    "name": "34.00",
    "description": "SOLDADOR",
    "canLeadTeam": false,
    "hierarchyLevel": 0,
    "createdAt": "2026-02-07T09:00:48.681Z",
    "updatedAt": "2026-02-07T09:00:48.681Z"
  },
  {
    "id": "b72ee7d8-e21a-4c76-8441-b85ddb324828",
    "companyId": null,
    "name": "35.00",
    "description": "SUB ENCARREGADO",
    "canLeadTeam": false,
    "hierarchyLevel": 0,
    "createdAt": "2026-02-07T09:00:48.777Z",
    "updatedAt": "2026-02-07T09:00:48.777Z"
  },
  {
    "id": "fc04f63e-ee43-42c4-813a-53e8f3eeeeca",
    "companyId": null,
    "name": "36.00",
    "description": "SUB ENCARREGADO DE MONTAGEM",
    "canLeadTeam": false,
    "hierarchyLevel": 0,
    "createdAt": "2026-02-07T09:00:48.865Z",
    "updatedAt": "2026-02-07T09:00:48.865Z"
  },
  {
    "id": "9c05b40a-0023-4a37-b144-a787a6e5c047",
    "companyId": null,
    "name": "37.00",
    "description": "SUB ENCARREGADO DE OBRA CIVIL",
    "canLeadTeam": false,
    "hierarchyLevel": 0,
    "createdAt": "2026-02-07T09:00:48.963Z",
    "updatedAt": "2026-02-07T09:00:48.963Z"
  },
  {
    "id": "afcc7af5-84b9-43b3-846e-9f13143aa60d",
    "companyId": null,
    "name": "38.00",
    "description": "ENCARREGADO DE CARPINTARIA",
    "canLeadTeam": false,
    "hierarchyLevel": 0,
    "createdAt": "2026-02-07T09:00:49.056Z",
    "updatedAt": "2026-02-07T09:00:49.056Z"
  },
  {
    "id": "e00b0240-4478-494b-93e6-8b025206dc08",
    "companyId": null,
    "name": "39.00",
    "description": "ENCARREGADO DE OBRA CIVIL",
    "canLeadTeam": false,
    "hierarchyLevel": 0,
    "createdAt": "2026-02-07T09:00:49.161Z",
    "updatedAt": "2026-02-07T09:00:49.161Z"
  },
  {
    "id": "1b88903f-3793-4cd3-b4ab-d789bf7ccbe7",
    "companyId": null,
    "name": "40.00",
    "description": "MOTORISTA",
    "canLeadTeam": false,
    "hierarchyLevel": 0,
    "createdAt": "2026-02-07T09:00:49.256Z",
    "updatedAt": "2026-02-07T09:00:49.256Z"
  },
  {
    "id": "1b7582f6-3c77-4af1-a7bc-db33eabfbf27",
    "companyId": null,
    "name": "41.00",
    "description": "TOPOGRAFO",
    "canLeadTeam": false,
    "hierarchyLevel": 0,
    "createdAt": "2026-02-07T09:00:49.347Z",
    "updatedAt": "2026-02-07T09:00:49.347Z"
  },
  {
    "id": "e59afc2f-2153-4986-ba89-92012e436f22",
    "companyId": null,
    "name": "42.00",
    "description": "PEDREIRO",
    "canLeadTeam": false,
    "hierarchyLevel": 0,
    "createdAt": "2026-02-07T09:00:49.440Z",
    "updatedAt": "2026-02-07T09:00:49.440Z"
  },
  {
    "id": "bbd43b08-9808-4f4f-94c6-7b7812979543",
    "companyId": null,
    "name": "43.00",
    "description": "SUB ENCARREGADO CIVIL",
    "canLeadTeam": false,
    "hierarchyLevel": 0,
    "createdAt": "2026-02-07T09:00:49.532Z",
    "updatedAt": "2026-02-07T09:00:49.532Z"
  },
  {
    "id": "3961db61-dc77-4405-b14e-de8790a3621b",
    "companyId": null,
    "name": "44.00",
    "description": "ANALISTA DE MEIO AMBIENTE",
    "canLeadTeam": false,
    "hierarchyLevel": 0,
    "createdAt": "2026-02-07T09:00:49.625Z",
    "updatedAt": "2026-02-07T09:00:49.625Z"
  },
  {
    "id": "d597735e-1afa-4e4f-bd0b-b236dc1c568e",
    "companyId": null,
    "name": "45.00",
    "description": "ANALISTA DE QUALIDADE",
    "canLeadTeam": false,
    "hierarchyLevel": 0,
    "createdAt": "2026-02-07T09:00:49.730Z",
    "updatedAt": "2026-02-07T09:00:49.730Z"
  },
  {
    "id": "fa6f086e-dc81-40d1-a042-12a132b0f94a",
    "companyId": null,
    "name": "46.00",
    "description": "ANALISTA T?CNICO",
    "canLeadTeam": false,
    "hierarchyLevel": 0,
    "createdAt": "2026-02-07T09:00:49.824Z",
    "updatedAt": "2026-02-07T09:00:49.824Z"
  },
  {
    "id": "b68ed900-39ad-49b1-a5de-f554cdadf250",
    "companyId": null,
    "name": "47.00",
    "description": "ASSISTENTE DE MEIO AMBIENTE",
    "canLeadTeam": false,
    "hierarchyLevel": 0,
    "createdAt": "2026-02-07T09:00:49.914Z",
    "updatedAt": "2026-02-07T09:00:49.914Z"
  },
  {
    "id": "7a988995-08e4-40a2-bf90-62925a9e5c14",
    "companyId": null,
    "name": "48.00",
    "description": "ASSISTENTE T?CNICO DE PLANEJAMENTO",
    "canLeadTeam": false,
    "hierarchyLevel": 0,
    "createdAt": "2026-02-07T09:00:50.007Z",
    "updatedAt": "2026-02-07T09:00:50.007Z"
  },
  {
    "id": "c21d42ad-7c7c-42cb-92f8-c35ec8eb8567",
    "companyId": null,
    "name": "49.00",
    "description": "ASSISTENTE T?CNICO",
    "canLeadTeam": false,
    "hierarchyLevel": 0,
    "createdAt": "2026-02-07T09:00:50.096Z",
    "updatedAt": "2026-02-07T09:00:50.096Z"
  },
  {
    "id": "e9083f8e-8082-4428-9656-0ef7bdc207de",
    "companyId": null,
    "name": "50.00",
    "description": "AUXILIAR ADMINISTRATIVO - TRANSPORTE",
    "canLeadTeam": false,
    "hierarchyLevel": 0,
    "createdAt": "2026-02-07T09:00:50.204Z",
    "updatedAt": "2026-02-07T09:00:50.204Z"
  },
  {
    "id": "a87c58e1-d85f-40e5-8fa4-3f4d231251e9",
    "companyId": null,
    "name": "51.00",
    "description": "ALMOXARIFE",
    "canLeadTeam": false,
    "hierarchyLevel": 0,
    "createdAt": "2026-02-07T09:00:50.311Z",
    "updatedAt": "2026-02-07T09:00:50.311Z"
  },
  {
    "id": "7c92f893-5a7b-4c14-94da-701c6891846e",
    "companyId": null,
    "name": "52.00",
    "description": "AUXILIAR DE ALMOXARIFADO",
    "canLeadTeam": false,
    "hierarchyLevel": 0,
    "createdAt": "2026-02-07T09:00:50.418Z",
    "updatedAt": "2026-02-07T09:00:50.418Z"
  },
  {
    "id": "5092f426-d2de-4ef5-8011-a8baa8168179",
    "companyId": null,
    "name": "53.00",
    "description": "AUXILIAR DE LABORATORISTA",
    "canLeadTeam": false,
    "hierarchyLevel": 0,
    "createdAt": "2026-02-07T09:00:50.520Z",
    "updatedAt": "2026-02-07T09:00:50.520Z"
  },
  {
    "id": "e93b4968-3ae7-4730-8150-422a94bea0ee",
    "companyId": null,
    "name": "54.00",
    "description": "AUXILIAR DE PLANEJAMENTO",
    "canLeadTeam": false,
    "hierarchyLevel": 0,
    "createdAt": "2026-02-07T09:00:50.631Z",
    "updatedAt": "2026-02-07T09:00:50.631Z"
  },
  {
    "id": "a57a10b2-4198-44d0-a6b6-f7769c7906de",
    "companyId": null,
    "name": "55.00",
    "description": "ASSISTENTE ADMINISTRATIVO",
    "canLeadTeam": false,
    "hierarchyLevel": 0,
    "createdAt": "2026-02-07T09:00:50.739Z",
    "updatedAt": "2026-02-07T09:00:50.739Z"
  },
  {
    "id": "37e9ef7e-5b4b-4a3b-9235-f7b6a36cf709",
    "companyId": null,
    "name": "56.00",
    "description": "AUXILIAR T?CNICO",
    "canLeadTeam": false,
    "hierarchyLevel": 0,
    "createdAt": "2026-02-07T09:00:50.850Z",
    "updatedAt": "2026-02-07T09:00:50.850Z"
  },
  {
    "id": "953311ba-55aa-4cc7-a6b4-05fe05ef44a6",
    "companyId": null,
    "name": "57.00",
    "description": "COORDENADOR DE PLANEJAMENTO",
    "canLeadTeam": false,
    "hierarchyLevel": 0,
    "createdAt": "2026-02-07T09:00:50.956Z",
    "updatedAt": "2026-02-07T09:00:50.956Z"
  },
  {
    "id": "ad4104d7-8167-461f-a936-4cf5c2ad40b0",
    "companyId": null,
    "name": "58.00",
    "description": "COORDENADOR FUNDI?RIO",
    "canLeadTeam": false,
    "hierarchyLevel": 0,
    "createdAt": "2026-02-07T09:00:51.061Z",
    "updatedAt": "2026-02-07T09:00:51.061Z"
  },
  {
    "id": "6f62753b-de0f-4005-a143-ff14ffebc525",
    "companyId": null,
    "name": "59.00",
    "description": "COORDENADOR T?CNICO",
    "canLeadTeam": false,
    "hierarchyLevel": 0,
    "createdAt": "2026-02-07T09:00:51.168Z",
    "updatedAt": "2026-02-07T09:00:51.168Z"
  },
  {
    "id": "cc54b087-47d2-4515-af30-fb655155833e",
    "companyId": null,
    "name": "60.00",
    "description": "COZINHEIRO",
    "canLeadTeam": false,
    "hierarchyLevel": 0,
    "createdAt": "2026-02-07T09:00:51.274Z",
    "updatedAt": "2026-02-07T09:00:51.274Z"
  },
  {
    "id": "d584f58e-cae1-4165-a415-920a5eb08f25",
    "companyId": null,
    "name": "61.00",
    "description": "ELETRICISTA FOR?A E CONTROLE",
    "canLeadTeam": false,
    "hierarchyLevel": 0,
    "createdAt": "2026-02-07T09:00:51.418Z",
    "updatedAt": "2026-02-07T09:00:51.418Z"
  },
  {
    "id": "64eb9adb-fb4e-4943-a6bd-d112cfa4ae0d",
    "companyId": null,
    "name": "62.00",
    "description": "AUXILIAR ADMINISTRATIVO",
    "canLeadTeam": false,
    "hierarchyLevel": 0,
    "createdAt": "2026-02-07T09:00:51.552Z",
    "updatedAt": "2026-02-07T09:00:51.552Z"
  },
  {
    "id": "00a5ceaf-94e1-41b0-a36e-b130d4ad6015",
    "companyId": null,
    "name": "63.00",
    "description": "ENCANADOR",
    "canLeadTeam": false,
    "hierarchyLevel": 0,
    "createdAt": "2026-02-07T09:00:51.660Z",
    "updatedAt": "2026-02-07T09:00:51.660Z"
  },
  {
    "id": "1f74e3a5-b2c0-4547-b639-519eb1905a8a",
    "companyId": null,
    "name": "64.00",
    "description": "AUXILIAR DE SERVI?OS GERAIS",
    "canLeadTeam": false,
    "hierarchyLevel": 0,
    "createdAt": "2026-02-07T09:00:51.754Z",
    "updatedAt": "2026-02-07T09:00:51.754Z"
  },
  {
    "id": "eecb1a2b-4292-4729-b22a-bd381d77f6b3",
    "companyId": null,
    "name": "65.00",
    "description": "ENCARREGADO DE LAN?AMENTO",
    "canLeadTeam": false,
    "hierarchyLevel": 0,
    "createdAt": "2026-02-07T09:00:51.857Z",
    "updatedAt": "2026-02-07T09:00:51.857Z"
  },
  {
    "id": "c4674856-0d97-43ea-a37d-0debbfb53b08",
    "companyId": null,
    "name": "66.00",
    "description": "ENCARREGADO DE SERVI?OS GERAIS",
    "canLeadTeam": false,
    "hierarchyLevel": 0,
    "createdAt": "2026-02-07T09:00:51.950Z",
    "updatedAt": "2026-02-07T09:00:51.950Z"
  },
  {
    "id": "2f989416-caac-4501-8ef7-2a67ecc0cb08",
    "companyId": null,
    "name": "67.00",
    "description": "ENCARREGADO DE TRANSPORTE",
    "canLeadTeam": false,
    "hierarchyLevel": 0,
    "createdAt": "2026-02-07T09:00:52.055Z",
    "updatedAt": "2026-02-07T09:00:52.055Z"
  },
  {
    "id": "d1f4097d-144b-4534-84c0-425bf30d8c44",
    "companyId": null,
    "name": "68.00",
    "description": "ENCARREGADO ELETRICISTA",
    "canLeadTeam": false,
    "hierarchyLevel": 0,
    "createdAt": "2026-02-07T09:00:52.151Z",
    "updatedAt": "2026-02-07T09:00:52.151Z"
  },
  {
    "id": "28212859-d865-40c7-9ef7-eba4a5140b9e",
    "companyId": null,
    "name": "69.00",
    "description": "ENGENHEIRO DE PLANEJAMENTO",
    "canLeadTeam": false,
    "hierarchyLevel": 0,
    "createdAt": "2026-02-07T09:00:52.249Z",
    "updatedAt": "2026-02-07T09:00:52.249Z"
  },
  {
    "id": "4631cd25-c851-446d-8489-e00819a0f8f8",
    "companyId": null,
    "name": "70.00",
    "description": "ELETRICISTA",
    "canLeadTeam": false,
    "hierarchyLevel": 0,
    "createdAt": "2026-02-07T09:00:52.516Z",
    "updatedAt": "2026-02-07T09:00:52.516Z"
  },
  {
    "id": "1876492c-ba2a-4222-9c99-b629fb67e96f",
    "companyId": null,
    "name": "71.00",
    "description": "OFICIAL DE MANUTEN??O PREDIAL",
    "canLeadTeam": false,
    "hierarchyLevel": 0,
    "createdAt": "2026-02-07T09:00:52.608Z",
    "updatedAt": "2026-02-07T09:00:52.608Z"
  },
  {
    "id": "ab2105d1-3753-4e98-a3da-85a9f6f97a44",
    "companyId": null,
    "name": "72.00",
    "description": "ENCARREGADO DE ALMOXARIFADO",
    "canLeadTeam": false,
    "hierarchyLevel": 0,
    "createdAt": "2026-02-07T09:00:52.698Z",
    "updatedAt": "2026-02-07T09:00:52.698Z"
  },
  {
    "id": "ef3dfcba-bf29-425c-9763-fdb1ae7878df",
    "companyId": null,
    "name": "73.00",
    "description": "SUPERVISOR CIVIL",
    "canLeadTeam": false,
    "hierarchyLevel": 0,
    "createdAt": "2026-02-07T09:00:52.775Z",
    "updatedAt": "2026-02-07T09:00:52.775Z"
  },
  {
    "id": "114481e0-9141-4610-a1f0-6f2b03a17e78",
    "companyId": null,
    "name": "74.00",
    "description": "SUPERVISOR DE ALMOXARIFADO",
    "canLeadTeam": false,
    "hierarchyLevel": 0,
    "createdAt": "2026-02-07T09:00:52.882Z",
    "updatedAt": "2026-02-07T09:00:52.882Z"
  },
  {
    "id": "5bbbe544-9588-481f-8761-b7cfb2fa6d09",
    "companyId": null,
    "name": "75.00",
    "description": "ENCARREGADO DE MATERIAIS",
    "canLeadTeam": false,
    "hierarchyLevel": 0,
    "createdAt": "2026-02-07T09:00:52.990Z",
    "updatedAt": "2026-02-07T09:00:52.990Z"
  },
  {
    "id": "853bb93e-cd58-4285-abbd-bf24429b7e82",
    "companyId": null,
    "name": "77.00",
    "description": "SUPERVISOR DE PLANEJAMENTO",
    "canLeadTeam": false,
    "hierarchyLevel": 0,
    "createdAt": "2026-02-07T09:00:53.174Z",
    "updatedAt": "2026-02-07T09:00:53.174Z"
  },
  {
    "id": "d5d56a7c-78a4-4682-9067-c6ed5b53c4d6",
    "companyId": null,
    "name": "78.00",
    "description": "T?CNICO DE LABORAT?RIO",
    "canLeadTeam": false,
    "hierarchyLevel": 0,
    "createdAt": "2026-02-07T09:00:53.260Z",
    "updatedAt": "2026-02-07T09:00:53.260Z"
  },
  {
    "id": "9c859a4c-f189-4c1d-ac0a-6e20b312d5cb",
    "companyId": null,
    "name": "79.00",
    "description": "T?CNICO DE MEIO AMBIENTE",
    "canLeadTeam": false,
    "hierarchyLevel": 0,
    "createdAt": "2026-02-07T09:00:53.371Z",
    "updatedAt": "2026-02-07T09:00:53.371Z"
  },
  {
    "id": "54932765-a133-496d-9d0f-1dddc79ab8dc",
    "companyId": null,
    "name": "81.00",
    "description": "T?CNICO DE QUALIDADE",
    "canLeadTeam": false,
    "hierarchyLevel": 0,
    "createdAt": "2026-02-07T09:00:53.554Z",
    "updatedAt": "2026-02-07T09:00:53.554Z"
  },
  {
    "id": "56722754-61ca-41d5-b9ae-30d80993d566",
    "companyId": null,
    "name": "83.00",
    "description": "VIGIA",
    "canLeadTeam": false,
    "hierarchyLevel": 0,
    "createdAt": "2026-02-07T09:00:53.727Z",
    "updatedAt": "2026-02-07T09:00:53.727Z"
  },
  {
    "id": "56287a0a-7af6-4459-b3a8-44e64d11e59f",
    "companyId": null,
    "name": "85.00",
    "description": "ENGENHEIRO RESIDENTE",
    "canLeadTeam": false,
    "hierarchyLevel": 0,
    "createdAt": "2026-02-07T09:00:53.907Z",
    "updatedAt": "2026-02-07T09:00:53.907Z"
  },
  {
    "id": "64f54f10-0a04-4765-b8c2-90b8621f479d",
    "companyId": null,
    "name": "87.00",
    "description": "SUPERVISOR DE PRODU??O",
    "canLeadTeam": false,
    "hierarchyLevel": 0,
    "createdAt": "2026-02-07T09:00:54.106Z",
    "updatedAt": "2026-02-07T09:00:54.106Z"
  },
  {
    "id": "5e37320a-6a14-43e5-8f8b-ee22b380cfa5",
    "companyId": null,
    "name": "88.00",
    "description": "SUPERVISOR DE CIVIL",
    "canLeadTeam": false,
    "hierarchyLevel": 0,
    "createdAt": "2026-02-07T09:00:54.194Z",
    "updatedAt": "2026-02-07T09:00:54.194Z"
  },
  {
    "id": "94aa275d-199b-49cf-ac63-ef7161587388",
    "companyId": null,
    "name": "89.00",
    "description": "SUPERVIOR DE LAN?AMENTO",
    "canLeadTeam": false,
    "hierarchyLevel": 0,
    "createdAt": "2026-02-07T09:00:54.287Z",
    "updatedAt": "2026-02-07T09:00:54.287Z"
  },
  {
    "id": "7944f860-673d-402c-9428-784c120b9d3f",
    "companyId": null,
    "name": "90.00",
    "description": "SUPERVISOR DE MONTAGEM",
    "canLeadTeam": false,
    "hierarchyLevel": 0,
    "createdAt": "2026-02-07T09:00:54.377Z",
    "updatedAt": "2026-02-07T09:00:54.377Z"
  },
  {
    "id": "47fe6db2-f8a0-4451-b356-beda381cb68d",
    "companyId": null,
    "name": "92.00",
    "description": "ANALISTA TECNICO",
    "canLeadTeam": false,
    "hierarchyLevel": 0,
    "createdAt": "2026-02-07T09:00:54.564Z",
    "updatedAt": "2026-02-07T09:00:54.564Z"
  },
  {
    "id": "d48749ea-dbaa-435f-801c-d133892b6eb0",
    "companyId": null,
    "name": "93.00",
    "description": "MOTORISTA DE COMBOIO",
    "canLeadTeam": false,
    "hierarchyLevel": 0,
    "createdAt": "2026-02-07T09:00:54.666Z",
    "updatedAt": "2026-02-07T09:00:54.666Z"
  },
  {
    "id": "5c13ab25-24a4-4b56-9bf1-86569477b445",
    "companyId": null,
    "name": "96.00",
    "description": "ANALISTA FINANCEIRO JR",
    "canLeadTeam": false,
    "hierarchyLevel": 0,
    "createdAt": "2026-02-07T09:00:54.942Z",
    "updatedAt": "2026-02-07T09:00:54.942Z"
  },
  {
    "id": "d8848ae2-c65e-4626-b48a-aec769ced256",
    "companyId": null,
    "name": "98.00",
    "description": "OPERADOR DE DRONE",
    "canLeadTeam": false,
    "hierarchyLevel": 0,
    "createdAt": "2026-02-07T09:00:55.128Z",
    "updatedAt": "2026-02-07T09:00:55.128Z"
  },
  {
    "id": "5ee226ab-375e-40a6-a38f-15a5e6000508",
    "companyId": null,
    "name": "99.00",
    "description": "AJUDANTE TA",
    "canLeadTeam": false,
    "hierarchyLevel": 0,
    "createdAt": "2026-02-07T09:00:55.208Z",
    "updatedAt": "2026-02-07T09:00:55.208Z"
  },
  {
    "id": "916f08c2-0f6c-4692-b17a-e0448cd000d3",
    "companyId": null,
    "name": "101.00",
    "description": "TECNICO DE PLANEJAMENTO",
    "canLeadTeam": false,
    "hierarchyLevel": 0,
    "createdAt": "2026-02-07T09:00:55.408Z",
    "updatedAt": "2026-02-07T09:00:55.408Z"
  },
  {
    "id": "018ca821-a290-4a98-a98a-e756d395c44b",
    "companyId": null,
    "name": "102.00",
    "description": "ASSITENTE T?CNICO",
    "canLeadTeam": false,
    "hierarchyLevel": 0,
    "createdAt": "2026-02-07T09:00:55.504Z",
    "updatedAt": "2026-02-07T09:00:55.504Z"
  },
  {
    "id": "cc8024ac-2827-4fda-896b-d09dd5ceddd3",
    "companyId": null,
    "name": "104.00",
    "description": "SUPERVISOR DE QUALIDADE PL",
    "canLeadTeam": false,
    "hierarchyLevel": 0,
    "createdAt": "2026-02-07T09:00:55.731Z",
    "updatedAt": "2026-02-07T09:00:55.731Z"
  },
  {
    "id": "8f025ed3-6783-4266-815e-abcaa710a546",
    "companyId": null,
    "name": "106.00",
    "description": "MOTORISTA DE CAMINHAO",
    "canLeadTeam": false,
    "hierarchyLevel": 0,
    "createdAt": "2026-02-07T09:00:55.911Z",
    "updatedAt": "2026-02-07T09:00:55.911Z"
  },
  {
    "id": "2ac65bc3-22e2-40c9-b705-cf232cd34fab",
    "companyId": null,
    "name": "107.00",
    "description": "ENGENHEIRO FLORESTAL",
    "canLeadTeam": false,
    "hierarchyLevel": 0,
    "createdAt": "2026-02-07T09:00:56.003Z",
    "updatedAt": "2026-02-07T09:00:56.003Z"
  },
  {
    "id": "fb9cbc92-e955-4f1f-acd4-a0f1db269b7c",
    "companyId": null,
    "name": "110.00",
    "description": "ENGENHEIRO DE SEGURAN?A",
    "canLeadTeam": false,
    "hierarchyLevel": 0,
    "createdAt": "2026-02-07T09:00:56.279Z",
    "updatedAt": "2026-02-07T09:00:56.279Z"
  },
  {
    "id": "6c4870ff-d9a8-46ea-af79-7ce054521ac0",
    "companyId": null,
    "name": "112.00",
    "description": "TECNICO EM SEGURAN?A DO TRABALHO",
    "canLeadTeam": false,
    "hierarchyLevel": 0,
    "createdAt": "2026-02-07T09:00:56.463Z",
    "updatedAt": "2026-02-07T09:00:56.463Z"
  },
  {
    "id": "0ed340ae-fbae-4edb-bede-677f2c4b8f98",
    "companyId": null,
    "name": "114.00",
    "description": "TECNICO DE ENFERMAGEM DO TRABALHO PL",
    "canLeadTeam": false,
    "hierarchyLevel": 0,
    "createdAt": "2026-02-07T09:00:56.646Z",
    "updatedAt": "2026-02-07T09:00:56.646Z"
  },
  {
    "id": "65236d2f-35bc-4e97-8268-8ff3c1db2f77",
    "companyId": null,
    "name": "115.00",
    "description": "MOTORISTA DE AMBULANCIA",
    "canLeadTeam": false,
    "hierarchyLevel": 0,
    "createdAt": "2026-02-07T09:00:56.734Z",
    "updatedAt": "2026-02-07T09:00:56.734Z"
  },
  {
    "id": "2a4958e9-6589-4f06-8561-4b2958ee3e81",
    "companyId": null,
    "name": "117.00",
    "description": "COORDENADOR DE MANUTEN??O",
    "canLeadTeam": false,
    "hierarchyLevel": 0,
    "createdAt": "2026-02-07T09:00:56.908Z",
    "updatedAt": "2026-02-07T09:00:56.908Z"
  },
  {
    "id": "28a39783-3eca-4ebf-a1a4-c96a48231334",
    "companyId": null,
    "name": "118.00",
    "description": "SUPERVISOR DE TRANSPORTE",
    "canLeadTeam": false,
    "hierarchyLevel": 0,
    "createdAt": "2026-02-07T09:00:57.014Z",
    "updatedAt": "2026-02-07T09:00:57.014Z"
  },
  {
    "id": "cb3b7344-72e3-48e9-9da5-a0c8341cedab",
    "companyId": null,
    "name": "120.00",
    "description": "ASSISTENTE DE LOGISTICA",
    "canLeadTeam": false,
    "hierarchyLevel": 0,
    "createdAt": "2026-02-07T09:00:57.216Z",
    "updatedAt": "2026-02-07T09:00:57.216Z"
  },
  {
    "id": "3ae58042-933d-4291-8dd2-0b0fb0a650df",
    "companyId": null,
    "name": "121.00",
    "description": "ENCARREGADO DE MANUTEN??O",
    "canLeadTeam": false,
    "hierarchyLevel": 0,
    "createdAt": "2026-02-07T09:00:57.311Z",
    "updatedAt": "2026-02-07T09:00:57.311Z"
  },
  {
    "id": "b0e3404b-53ee-4b62-b49d-f291d0f0ac70",
    "companyId": null,
    "name": "122.00",
    "description": "ENCARREGADO ALMOXARIFE",
    "canLeadTeam": false,
    "hierarchyLevel": 0,
    "createdAt": "2026-02-07T09:00:57.406Z",
    "updatedAt": "2026-02-07T09:00:57.406Z"
  },
  {
    "id": "d7a1a9ef-8168-4236-a8df-87c324d56063",
    "companyId": null,
    "name": "124.00",
    "description": "SUB ENCARREGADO DE SERVI?OS GERAIS",
    "canLeadTeam": false,
    "hierarchyLevel": 0,
    "createdAt": "2026-02-07T09:00:57.570Z",
    "updatedAt": "2026-02-07T09:00:57.570Z"
  },
  {
    "id": "83363530-2ea7-4f62-8bf4-c7277ea2e069",
    "companyId": null,
    "name": "127.00",
    "description": "SUPERVISOR DE MONTAGEM",
    "canLeadTeam": false,
    "hierarchyLevel": 0,
    "createdAt": "2026-02-07T09:00:57.836Z",
    "updatedAt": "2026-02-07T09:00:57.836Z"
  },
  {
    "id": "145fbd20-1f8c-4c2a-b5f7-8818a5102706",
    "companyId": null,
    "name": "129.00",
    "description": "ANALISTA DE RECURSOS HUMANOS",
    "canLeadTeam": false,
    "hierarchyLevel": 0,
    "createdAt": "2026-02-07T09:00:58.018Z",
    "updatedAt": "2026-02-07T09:00:58.018Z"
  },
  {
    "id": "0c4778ed-c456-4db4-970f-da4dc31dc4e8",
    "companyId": null,
    "name": "130.00",
    "description": "SUPERVISOR DE QUALIDADE",
    "canLeadTeam": false,
    "hierarchyLevel": 0,
    "createdAt": "2026-02-07T09:00:58.144Z",
    "updatedAt": "2026-02-07T09:00:58.144Z"
  },
  {
    "id": "e37c372c-43f1-4fa3-b3e2-2e0f763e3a64",
    "companyId": null,
    "name": "132.00",
    "description": "AUX. T?CNICO",
    "canLeadTeam": false,
    "hierarchyLevel": 0,
    "createdAt": "2026-02-07T09:00:58.345Z",
    "updatedAt": "2026-02-07T09:00:58.345Z"
  },
  {
    "id": "43bc34bd-a626-4d6e-9f98-56ce481e7cfc",
    "companyId": null,
    "name": "133.00",
    "description": "ANALISTA FINANCEIRO",
    "canLeadTeam": false,
    "hierarchyLevel": 0,
    "createdAt": "2026-02-07T09:00:58.433Z",
    "updatedAt": "2026-02-07T09:00:58.433Z"
  },
  {
    "id": "d11bf5bd-13d0-4068-bf5f-c83934b4c534",
    "companyId": null,
    "name": "135.00",
    "description": "ENG. SEGURAN?A DO TRABALHO",
    "canLeadTeam": false,
    "hierarchyLevel": 0,
    "createdAt": "2026-02-07T09:00:58.573Z",
    "updatedAt": "2026-02-07T09:00:58.573Z"
  },
  {
    "id": "6d728e6e-7d59-4677-a313-c7b66d7e52a4",
    "companyId": null,
    "name": "137.00",
    "description": "T?CNICO FUNDI?RIO",
    "canLeadTeam": false,
    "hierarchyLevel": 0,
    "createdAt": "2026-02-07T09:00:58.739Z",
    "updatedAt": "2026-02-07T09:00:58.739Z"
  },
  {
    "id": "1b4dc8d5-5f47-47c0-91ef-3dd2d17661cd",
    "companyId": null,
    "name": "138.00",
    "description": "SUPERVISOR DE TRANSPORTE",
    "canLeadTeam": false,
    "hierarchyLevel": 0,
    "createdAt": "2026-02-07T09:00:58.852Z",
    "updatedAt": "2026-02-07T09:00:58.852Z"
  },
  {
    "id": "6cc2dbca-4970-4ab1-9f0c-2e1fc86e8248",
    "companyId": null,
    "name": "76.00",
    "description": "SUPERVISOR DE OBRAS",
    "canLeadTeam": false,
    "hierarchyLevel": 0,
    "createdAt": "2026-02-07T09:00:53.082Z",
    "updatedAt": "2026-02-07T09:00:53.082Z"
  },
  {
    "id": "2779314e-9d04-454d-80e0-8608fba3736c",
    "companyId": null,
    "name": "80.00",
    "description": "T?CNICO DE PROJETOS",
    "canLeadTeam": false,
    "hierarchyLevel": 0,
    "createdAt": "2026-02-07T09:00:53.465Z",
    "updatedAt": "2026-02-07T09:00:53.465Z"
  },
  {
    "id": "0f0aab7c-d0a2-4cb4-bd10-0f2afe8e45fa",
    "companyId": null,
    "name": "82.00",
    "description": "T?CNICO DE SEGURAN?A DO TRABALHO",
    "canLeadTeam": false,
    "hierarchyLevel": 0,
    "createdAt": "2026-02-07T09:00:53.629Z",
    "updatedAt": "2026-02-07T09:00:53.629Z"
  },
  {
    "id": "9de2abc0-bf6e-4411-893c-bb9f5cb79fea",
    "companyId": null,
    "name": "84.00",
    "description": "GERENTE DE PROJETOS",
    "canLeadTeam": false,
    "hierarchyLevel": 0,
    "createdAt": "2026-02-07T09:00:53.815Z",
    "updatedAt": "2026-02-07T09:00:53.815Z"
  },
  {
    "id": "9aae60a2-5c79-41e0-b734-c8a15bdd4666",
    "companyId": null,
    "name": "86.00",
    "description": "COORDENADOR DE OBRAS",
    "canLeadTeam": false,
    "hierarchyLevel": 0,
    "createdAt": "2026-02-07T09:00:54.011Z",
    "updatedAt": "2026-02-07T09:00:54.011Z"
  },
  {
    "id": "9b38c51b-a203-46e4-adba-7b1e20920b54",
    "companyId": null,
    "name": "91.00",
    "description": "ANALISTA DE RECURSOS HUMANOS JR",
    "canLeadTeam": false,
    "hierarchyLevel": 0,
    "createdAt": "2026-02-07T09:00:54.470Z",
    "updatedAt": "2026-02-07T09:00:54.470Z"
  },
  {
    "id": "917c7bdb-3107-4c0d-8ae5-1b04b29c8f8d",
    "companyId": null,
    "name": "94.00",
    "description": "COORDENADOR ADMINISTRATIVO",
    "canLeadTeam": false,
    "hierarchyLevel": 0,
    "createdAt": "2026-02-07T09:00:54.760Z",
    "updatedAt": "2026-02-07T09:00:54.760Z"
  },
  {
    "id": "65338849-1e77-4b63-9947-c1975237cd3a",
    "companyId": null,
    "name": "95.00",
    "description": "SUPERVISOR ADMINISTRATIVO",
    "canLeadTeam": false,
    "hierarchyLevel": 0,
    "createdAt": "2026-02-07T09:00:54.854Z",
    "updatedAt": "2026-02-07T09:00:54.854Z"
  },
  {
    "id": "a52101d5-d9a1-4b05-a424-d9f02d1b49a6",
    "companyId": null,
    "name": "97.00",
    "description": "ANALISTA DE TI",
    "canLeadTeam": false,
    "hierarchyLevel": 0,
    "createdAt": "2026-02-07T09:00:55.038Z",
    "updatedAt": "2026-02-07T09:00:55.038Z"
  },
  {
    "id": "f8b48f71-19c9-47d2-8ee2-73c1a7cc6a54",
    "companyId": null,
    "name": "100.00",
    "description": "COORDENADOR DE  PLANEJAMENTO",
    "canLeadTeam": false,
    "hierarchyLevel": 0,
    "createdAt": "2026-02-07T09:00:55.302Z",
    "updatedAt": "2026-02-07T09:00:55.302Z"
  },
  {
    "id": "5e84953a-0b49-450d-970f-e6026df522d2",
    "companyId": null,
    "name": "103.00",
    "description": "AUXILIAR TECNICO",
    "canLeadTeam": false,
    "hierarchyLevel": 0,
    "createdAt": "2026-02-07T09:00:55.638Z",
    "updatedAt": "2026-02-07T09:00:55.638Z"
  },
  {
    "id": "6591553e-42c8-4bc7-90ba-18aa20da57ec",
    "companyId": null,
    "name": "105.00",
    "description": "TECNICO EM QUALIDADE JR",
    "canLeadTeam": false,
    "hierarchyLevel": 0,
    "createdAt": "2026-02-07T09:00:55.819Z",
    "updatedAt": "2026-02-07T09:00:55.819Z"
  },
  {
    "id": "89acc4e6-e3dd-426c-b0fd-47522a768916",
    "companyId": null,
    "name": "108.00",
    "description": "TECNICO EM MEIO AMBIENTE PL",
    "canLeadTeam": false,
    "hierarchyLevel": 0,
    "createdAt": "2026-02-07T09:00:56.110Z",
    "updatedAt": "2026-02-07T09:00:56.110Z"
  },
  {
    "id": "e16ca941-4ed2-46a0-aa42-efb032e574b2",
    "companyId": null,
    "name": "109.00",
    "description": "ASSISTENTE DE MEIO AMBIENTE",
    "canLeadTeam": false,
    "hierarchyLevel": 0,
    "createdAt": "2026-02-07T09:00:56.184Z",
    "updatedAt": "2026-02-07T09:00:56.184Z"
  },
  {
    "id": "ae781a1d-c4db-41ad-8b2c-b1ea05d40058",
    "companyId": null,
    "name": "111.00",
    "description": "MEDICO DO TRABALHO",
    "canLeadTeam": false,
    "hierarchyLevel": 0,
    "createdAt": "2026-02-07T09:00:56.371Z",
    "updatedAt": "2026-02-07T09:00:56.371Z"
  },
  {
    "id": "db583b68-e764-4a85-b7ad-524fc9103f6f",
    "companyId": null,
    "name": "113.00",
    "description": "TECNICO EM SEGURAN?A DO TRABALHO PL",
    "canLeadTeam": false,
    "hierarchyLevel": 0,
    "createdAt": "2026-02-07T09:00:56.554Z",
    "updatedAt": "2026-02-07T09:00:56.554Z"
  },
  {
    "id": "3388c74a-1f94-4425-80d8-2b09f55f44c1",
    "companyId": null,
    "name": "116.00",
    "description": "MOTORISTA SOCORRISTA",
    "canLeadTeam": false,
    "hierarchyLevel": 0,
    "createdAt": "2026-02-07T09:00:56.812Z",
    "updatedAt": "2026-02-07T09:00:56.812Z"
  },
  {
    "id": "a79a4da8-327c-4a5a-9ca9-29cad0bccf88",
    "companyId": null,
    "name": "119.00",
    "description": "AUXILIAR ADMINISTRATIVO DE TRANSPORTE",
    "canLeadTeam": false,
    "hierarchyLevel": 0,
    "createdAt": "2026-02-07T09:00:57.114Z",
    "updatedAt": "2026-02-07T09:00:57.114Z"
  },
  {
    "id": "8905e598-c529-402f-8013-a956a6e393c4",
    "companyId": null,
    "name": "123.00",
    "description": "ENCARREGADO DE SERVICOS GERAIS",
    "canLeadTeam": false,
    "hierarchyLevel": 0,
    "createdAt": "2026-02-07T09:00:57.494Z",
    "updatedAt": "2026-02-07T09:00:57.494Z"
  },
  {
    "id": "161f7311-678a-4c2d-becd-2a9d9b47d138",
    "companyId": null,
    "name": "125.00",
    "description": "SUPERVISOR DE LAN?AMENTO",
    "canLeadTeam": false,
    "hierarchyLevel": 0,
    "createdAt": "2026-02-07T09:00:57.654Z",
    "updatedAt": "2026-02-07T09:00:57.654Z"
  },
  {
    "id": "ed9c0bbd-7639-4300-98dc-48d825083d53",
    "companyId": null,
    "name": "126.00",
    "description": "ELETRICISTA DE MANUTENCAO",
    "canLeadTeam": false,
    "hierarchyLevel": 0,
    "createdAt": "2026-02-07T09:00:57.742Z",
    "updatedAt": "2026-02-07T09:00:57.742Z"
  },
  {
    "id": "08a2ab11-6654-42a1-824d-800bf3242fab",
    "companyId": null,
    "name": "128.00",
    "description": "SUPERVISOR DE OBRAS CIVIL",
    "canLeadTeam": false,
    "hierarchyLevel": 0,
    "createdAt": "2026-02-07T09:00:57.929Z",
    "updatedAt": "2026-02-07T09:00:57.929Z"
  },
  {
    "id": "eeac803f-72c1-4676-9bc8-ed586ddac2f8",
    "companyId": null,
    "name": "131.00",
    "description": "SUPERVISOR DE SEGURAN?A DO TRABALHO",
    "canLeadTeam": false,
    "hierarchyLevel": 0,
    "createdAt": "2026-02-07T09:00:58.250Z",
    "updatedAt": "2026-02-07T09:00:58.250Z"
  },
  {
    "id": "c9ec84eb-4a3b-41ac-a4e8-bb810aced753",
    "companyId": null,
    "name": "134.00",
    "description": "T?CNICO DE PLANEJAMENTO",
    "canLeadTeam": false,
    "hierarchyLevel": 0,
    "createdAt": "2026-02-07T09:00:58.510Z",
    "updatedAt": "2026-02-07T09:00:58.510Z"
  },
  {
    "id": "a108b37f-7ead-4a66-81a7-44277df723ed",
    "companyId": null,
    "name": "136.00",
    "description": "ENG? RESIDENTE",
    "canLeadTeam": false,
    "hierarchyLevel": 0,
    "createdAt": "2026-02-07T09:00:58.665Z",
    "updatedAt": "2026-02-07T09:00:58.665Z"
  }
]